{
  "className": "qx.event.handler.OrientationCore",
  "packageName": "qx.event.handler",
  "name": "OrientationCore",
  "superClass": "Object",
  "interfaces": [
    "qx.core.IDisposable"
  ],
  "mixins": [],
  "functionName": null,
  "clazz": {
    "location": {
      "start": {
        "line": 41,
        "column": 0
      },
      "end": {
        "line": 158,
        "column": 3
      }
    },
    "jsdoc": {
      "@description": [
        {
          "name": "@description",
          "body": "<pre><code>*****************************************************************\n</code></pre>\n<p>qooxdoo - the new era of web development\n   http://qooxdoo.org\n   Copyright:\n     2004-2012 1&amp;1 Internet AG, Germany, http://www.1und1.de\n   License:\n     MIT: https://opensource.org/licenses/MIT\n     See the LICENSE file in the project's top-level directory for details.\n   Authors:\n Tino Butz (tbtz)\n Daniel Wagner (danielwagner)\n   ======================================================================\n   This class contains code based on the following work:\n Unify Project\n     Homepage:\n       http://unify-project.org\n     Copyright:\n       2009-2010 Deutsche Telekom AG, Germany, http://telekom.com\n     License:\n       MIT: http://www.opensource.org/licenses/mit-license.php\n    <strong><em><em></em></strong><strong><em></em></em></strong><strong><em><em></em></strong><strong><em></em></em></strong><strong><em><em></em></strong><strong><em></em></em></strong><strong><em><em></em></strong><strong><em></em></em></strong><strong><em><em></em></strong></em>*</p>"
        },
        {
          "name": "@description",
          "body": "<p>Listens for native orientation change events\n NOTE: Instances of this class must be disposed of after use</p>"
        }
      ]
    }
  },
  "type": "class",
  "construct": {
    "location": {
      "start": {
        "line": 51,
        "column": 14
      },
      "end": {
        "line": 56,
        "column": 3
      }
    },
    "jsdoc": {
      "@description": [
        {
          "name": "@description",
          "body": ""
        }
      ],
      "@param": [
        {
          "name": "@param",
          "body": "targetWindow {Window} DOM window object",
          "paramName": "targetWindow",
          "description": " DOM window object",
          "type": "qx.event.handler.Window"
        },
        {
          "name": "@param",
          "body": "emitter {qx.event.Emitter} Event emitter object",
          "paramName": "emitter",
          "description": " Event emitter object",
          "type": "qx.event.Emitter"
        }
      ]
    }
  },
  "members": {
    "__emitter": {
      "location": {
        "start": {
          "line": 62,
          "column": 4
        },
        "end": {
          "line": 62,
          "column": 20
        }
      },
      "type": "variable",
      "access": "private"
    },
    "_window": {
      "location": {
        "start": {
          "line": 63,
          "column": 4
        },
        "end": {
          "line": 63,
          "column": 18
        }
      },
      "type": "variable",
      "access": "protected"
    },
    "_currentOrientation": {
      "location": {
        "start": {
          "line": 64,
          "column": 4
        },
        "end": {
          "line": 64,
          "column": 30
        }
      },
      "type": "variable",
      "access": "protected"
    },
    "__onNativeWrapper": {
      "location": {
        "start": {
          "line": 65,
          "column": 4
        },
        "end": {
          "line": 65,
          "column": 28
        }
      },
      "type": "variable",
      "access": "private"
    },
    "__nativeEventType": {
      "location": {
        "start": {
          "line": 66,
          "column": 4
        },
        "end": {
          "line": 66,
          "column": 28
        }
      },
      "type": "variable",
      "access": "private"
    },
    "_initObserver": {
      "location": {
        "start": {
          "line": 79,
          "column": 4
        },
        "end": {
          "line": 92,
          "column": 5
        }
      },
      "jsdoc": {
        "@description": [
          {
            "name": "@description",
            "body": "<pre><code>---------------------------------------------------------------------------\n  OBSERVER INIT\n---------------------------------------------------------------------------\n</code></pre>"
          },
          {
            "name": "@description",
            "body": "<p>Initializes the native orientation change event listeners.</p>"
          }
        ]
      },
      "type": "function",
      "access": "protected"
    },
    "_stopObserver": {
      "location": {
        "start": {
          "line": 105,
          "column": 4
        },
        "end": {
          "line": 109,
          "column": 5
        }
      },
      "jsdoc": {
        "@description": [
          {
            "name": "@description",
            "body": "<pre><code>---------------------------------------------------------------------------\n  OBSERVER STOP\n---------------------------------------------------------------------------\n</code></pre>"
          },
          {
            "name": "@description",
            "body": "<p>Disconnects the native orientation change event listeners.</p>"
          }
        ]
      },
      "type": "function",
      "access": "protected"
    },
    "_onNative": {
      "location": {
        "start": {
          "line": 125,
          "column": 4
        },
        "end": {
          "line": 141,
          "column": 5
        }
      },
      "jsdoc": {
        "@description": [
          {
            "name": "@description",
            "body": "<pre><code>---------------------------------------------------------------------------\n  NATIVE EVENT OBSERVERS\n---------------------------------------------------------------------------\n</code></pre>"
          },
          {
            "name": "@description",
            "body": "<p>Handler for the native orientation change event.</p>"
          }
        ],
        "@signature": [
          {
            "name": "@signature",
            "body": "function(domEvent)"
          }
        ],
        "@param": [
          {
            "name": "@param",
            "body": "domEvent {Event} The touch event from the browser.",
            "paramName": "domEvent",
            "description": " The touch event from the browser.",
            "type": "Event"
          }
        ]
      },
      "type": "function",
      "access": "protected"
    },
    "dispose": {
      "type": "function",
      "name": "dispose",
      "abstract": true,
      "mixin": false,
      "inherited": true,
      "access": "public",
      "overriddenFrom": "qx.core.IDisposable"
    }
  },
  "destruct": {
    "location": {
      "start": {
        "line": 152,
        "column": 13
      },
      "end": {
        "line": 156,
        "column": 3
      }
    },
    "jsdoc": {
      "@description": [
        {
          "name": "@description",
          "body": "<pre><code>**********************************************************************\n DESTRUCTOR\n**********************************************************************\n</code></pre>"
        }
      ]
    }
  },
  "abstract": true,
  "descendants": []
}