{
  "version": 0.3,
  "lastModified": 1782594888990,
  "lastModifiedIso": "2026-06-27T21:14:48.990Z",
  "classFilename": "../../node_modules/@qooxdoo/framework/source/class/qx/ui/core/Blocker.js",
  "type": "class",
  "location": {
    "start": {
      "line": 28,
      "column": 0,
      "index": 808
    },
    "end": {
      "line": 533,
      "column": 3,
      "index": 14801
    }
  },
  "className": "qx.ui.core.Blocker",
  "jsdoc": {
    "raw": [
      "*",
      " * This class blocks events and can be included into all widgets.",
      " *",
      " * The {@link #block} and {@link #unblock} methods provided by this class can be used",
      " * to block any event from the widget. When blocked,",
      " * the blocker widget overlays the widget to block, including the padding area.",
      " *",
      " * @ignore(qx.ui.root.Abstract)",
      " "
    ],
    "@description": [
      {
        "name": "@description",
        "body": "<p>This class blocks events and can be included into all widgets.\n The {@link #block} and {@link #unblock} methods provided by this class can be used\n to block any event from the widget. When blocked,\n the blocker widget overlays the widget to block, including the padding area.</p>"
      }
    ],
    "@ignore": [
      {
        "name": "@ignore",
        "body": "qx.ui.root.Abstract"
      }
    ]
  },
  "superClass": "qx.core.Object",
  "events": {
    "blocked": {
      "type": "qx.event.type.Event",
      "jsdoc": {
        "raw": [
          "*",
          "     * Fires after {@link #block} executed.",
          "     "
        ],
        "@description": [
          {
            "name": "@description",
            "body": "<p>Fires after {@link #block} executed.</p>"
          }
        ]
      },
      "location": {
        "start": {
          "line": 35,
          "column": 4,
          "index": 951
        },
        "end": {
          "line": 35,
          "column": 34,
          "index": 981
        }
      }
    },
    "unblocked": {
      "type": "qx.event.type.Event",
      "jsdoc": {
        "raw": [
          "*",
          "     * Fires after {@link #unblock} executed.",
          "     "
        ],
        "@description": [
          {
            "name": "@description",
            "body": "<p>Fires after {@link #unblock} executed.</p>"
          }
        ]
      },
      "location": {
        "start": {
          "line": 40,
          "column": 4,
          "index": 1050
        },
        "end": {
          "line": 40,
          "column": 36,
          "index": 1082
        }
      }
    }
  },
  "construct": {
    "type": "function",
    "params": [
      {
        "name": "widget"
      }
    ],
    "location": {
      "start": {
        "line": 48,
        "column": 2,
        "index": 1234
      },
      "end": {
        "line": 75,
        "column": 3,
        "index": 1992
      }
    }
  },
  "properties": {
    "color": {
      "location": {
        "start": {
          "line": 87,
          "column": 4,
          "index": 2246
        },
        "end": {
          "line": 93,
          "column": 5,
          "index": 2372
        }
      },
      "json": {
        "check": "Color",
        "nullable": true,
        "apply": "_applyColor",
        "themeable": true
      },
      "jsdoc": {
        "raw": [
          "*",
          "     * Color of the blocker",
          "     "
        ],
        "@description": [
          {
            "name": "@description",
            "body": "<p>Color of the blocker</p>"
          }
        ]
      },
      "appearsIn": []
    },
    "opacity": {
      "location": {
        "start": {
          "line": 98,
          "column": 4,
          "index": 2425
        },
        "end": {
          "line": 103,
          "column": 5,
          "index": 2531
        }
      },
      "json": {
        "check": "Number",
        "init": 1,
        "apply": "_applyOpacity",
        "themeable": true
      },
      "jsdoc": {
        "raw": [
          "*",
          "     * Opacity of the blocker",
          "     "
        ],
        "@description": [
          {
            "name": "@description",
            "body": "<p>Opacity of the blocker</p>"
          }
        ]
      },
      "appearsIn": []
    },
    "keepBlockerActive": {
      "location": {
        "start": {
          "line": 120,
          "column": 4,
          "index": 3259
        },
        "end": {
          "line": 123,
          "column": 5,
          "index": 3327
        }
      },
      "json": {
        "check": "Boolean",
        "init": false
      },
      "jsdoc": {
        "raw": [
          "*",
          "     * If this property is enabled, the blocker created with {@link #block}",
          "     * will always stay activated. This means that the blocker then gets all keyboard",
          "     * events, this is useful to block keyboard input on other widgets.",
          "     * Take care that only one blocker instance will be kept active, otherwise your",
          "     * browser will freeze.",
          "     *",
          "     * Setting this property to true is ignored, if the blocker is attached to a",
          "     * widget with a focus handler, as this would mean that the focus handler",
          "     * tries to activate the widget behind the blocker.",
          "     *",
          "     * fixes:",
          "     *     https://github.com/qooxdoo/qooxdoo/issues/9449",
          "     *     https://github.com/qooxdoo/qooxdoo/issues/8104",
          "     "
        ],
        "@description": [
          {
            "name": "@description",
            "body": "<p>If this property is enabled, the blocker created with {@link #block}\n will always stay activated. This means that the blocker then gets all keyboard\n events, this is useful to block keyboard input on other widgets.\n Take care that only one blocker instance will be kept active, otherwise your\n browser will freeze.\n Setting this property to true is ignored, if the blocker is attached to a\n widget with a focus handler, as this would mean that the focus handler\n tries to activate the widget behind the blocker.\n fixes:\n     https://github.com/qooxdoo/qooxdoo/issues/9449\n     https://github.com/qooxdoo/qooxdoo/issues/8104</p>"
          }
        ]
      },
      "appearsIn": []
    }
  },
  "members": {
    "__blocker": {
      "jsdoc": null,
      "access": "private",
      "location": {
        "start": {
          "line": 133,
          "column": 4,
          "index": 3535
        },
        "end": {
          "line": 133,
          "column": 19,
          "index": 3550
        }
      },
      "appearsIn": []
    },
    "__blockerCount": {
      "jsdoc": null,
      "access": "private",
      "location": {
        "start": {
          "line": 134,
          "column": 4,
          "index": 3556
        },
        "end": {
          "line": 134,
          "column": 21,
          "index": 3573
        }
      },
      "appearsIn": []
    },
    "__blockingContent": {
      "jsdoc": null,
      "access": "private",
      "location": {
        "start": {
          "line": 135,
          "column": 4,
          "index": 3579
        },
        "end": {
          "line": 135,
          "column": 28,
          "index": 3603
        }
      },
      "appearsIn": []
    },
    "__activeElements": {
      "jsdoc": null,
      "access": "private",
      "location": {
        "start": {
          "line": 137,
          "column": 4,
          "index": 3610
        },
        "end": {
          "line": 137,
          "column": 26,
          "index": 3632
        }
      },
      "appearsIn": []
    },
    "__focusElements": {
      "jsdoc": null,
      "access": "private",
      "location": {
        "start": {
          "line": 138,
          "column": 4,
          "index": 3638
        },
        "end": {
          "line": 138,
          "column": 25,
          "index": 3659
        }
      },
      "appearsIn": []
    },
    "__timer": {
      "jsdoc": null,
      "access": "private",
      "location": {
        "start": {
          "line": 140,
          "column": 4,
          "index": 3666
        },
        "end": {
          "line": 140,
          "column": 17,
          "index": 3679
        }
      },
      "appearsIn": []
    },
    "_widget": {
      "jsdoc": null,
      "access": "protected",
      "location": {
        "start": {
          "line": 142,
          "column": 4,
          "index": 3686
        },
        "end": {
          "line": 142,
          "column": 17,
          "index": 3699
        }
      },
      "appearsIn": []
    },
    "_isRoot": {
      "jsdoc": null,
      "access": "protected",
      "location": {
        "start": {
          "line": 143,
          "column": 4,
          "index": 3705
        },
        "end": {
          "line": 143,
          "column": 18,
          "index": 3719
        }
      },
      "appearsIn": []
    },
    "__appearListener": {
      "jsdoc": null,
      "access": "private",
      "location": {
        "start": {
          "line": 145,
          "column": 4,
          "index": 3726
        },
        "end": {
          "line": 145,
          "column": 26,
          "index": 3748
        }
      },
      "appearsIn": []
    },
    "__onBoundsChange": {
      "jsdoc": {
        "raw": [
          "*",
          "     * Adjust html element size on layout resizes.",
          "     *",
          "     * @param e {qx.event.type.Data} event object",
          "     "
        ],
        "@description": [
          {
            "name": "@description",
            "body": "<p>Adjust html element size on layout resizes.</p>"
          }
        ],
        "@param": [
          {
            "name": "@param",
            "body": "e {qx.event.type.Data} event object",
            "paramName": "e",
            "description": " event object",
            "type": "qx.event.type.Data"
          }
        ]
      },
      "access": "private",
      "location": {
        "start": {
          "line": 152,
          "column": 4,
          "index": 3879
        },
        "end": {
          "line": 158,
          "column": 5,
          "index": 4016
        }
      },
      "type": "function",
      "params": [
        {
          "name": "e",
          "type": "qx.event.type.Data"
        }
      ],
      "appearsIn": []
    },
    "__onWidgetAppear": {
      "jsdoc": {
        "raw": [
          "*",
          "     * Widget re-appears: Update blocker size/position and attach to (new) parent",
          "     "
        ],
        "@description": [
          {
            "name": "@description",
            "body": "<p>Widget re-appears: Update blocker size/position and attach to (new) parent</p>"
          }
        ]
      },
      "access": "private",
      "location": {
        "start": {
          "line": 163,
          "column": 4,
          "index": 4121
        },
        "end": {
          "line": 173,
          "column": 5,
          "index": 4465
        }
      },
      "type": "function",
      "params": [],
      "appearsIn": []
    },
    "__onWidgetDisappear": {
      "jsdoc": {
        "raw": [
          "*",
          "     * Remove the blocker if the widget disappears",
          "     "
        ],
        "@description": [
          {
            "name": "@description",
            "body": "<p>Remove the blocker if the widget disappears</p>"
          }
        ]
      },
      "access": "private",
      "location": {
        "start": {
          "line": 178,
          "column": 4,
          "index": 4539
        },
        "end": {
          "line": 183,
          "column": 5,
          "index": 4762
        }
      },
      "type": "function",
      "params": [],
      "appearsIn": []
    },
    "_updateBlockerBounds": {
      "jsdoc": {
        "raw": [
          "*",
          "     * set the blocker's size and position",
          "     * @param bounds {Map} Map with the new width, height, left and top values",
          "     "
        ],
        "@description": [
          {
            "name": "@description",
            "body": "<p>set the blocker's size and position</p>"
          }
        ],
        "@param": [
          {
            "name": "@param",
            "body": "bounds {Map} Map with the new width, height, left and top values",
            "paramName": "bounds",
            "description": " Map with the new width, height, left and top values",
            "type": "Map<any, any>"
          }
        ]
      },
      "access": "protected",
      "location": {
        "start": {
          "line": 189,
          "column": 4,
          "index": 4907
        },
        "end": {
          "line": 202,
          "column": 5,
          "index": 5449
        }
      },
      "type": "function",
      "params": [
        {
          "name": "bounds",
          "type": "Map<any, any>"
        }
      ],
      "appearsIn": []
    },
    "_applyColor": {
      "jsdoc": {
        "raw": [
          " property apply"
        ]
      },
      "access": "protected",
      "location": {
        "start": {
          "line": 205,
          "column": 4,
          "index": 5478
        },
        "end": {
          "line": 208,
          "column": 5,
          "index": 5637
        }
      },
      "type": "function",
      "params": [
        {
          "name": "value"
        },
        {
          "name": "old"
        }
      ],
      "appearsIn": []
    },
    "_applyOpacity": {
      "jsdoc": {
        "raw": [
          " property apply"
        ]
      },
      "access": "protected",
      "location": {
        "start": {
          "line": 211,
          "column": 4,
          "index": 5666
        },
        "end": {
          "line": 213,
          "column": 5,
          "index": 5748
        }
      },
      "type": "function",
      "params": [
        {
          "name": "value"
        },
        {
          "name": "old"
        }
      ],
      "appearsIn": []
    },
    "_onChangeTheme": {
      "jsdoc": {
        "raw": [
          "*",
          "     * Handler for the theme change.",
          "     * @signature function()",
          "     "
        ],
        "@description": [
          {
            "name": "@description",
            "body": "<p>Handler for the theme change.</p>"
          }
        ],
        "@signature": [
          {
            "name": "@signature",
            "body": "function()"
          }
        ]
      },
      "access": "protected",
      "location": {
        "start": {
          "line": 219,
          "column": 4,
          "index": 5837
        },
        "end": {
          "line": 224,
          "column": 6,
          "index": 5988
        }
      },
      "appearsIn": []
    },
    "__setBlockersStyle": {
      "jsdoc": {
        "raw": [
          "*",
          "     * Set the style to all blockers (blocker and content blocker).",
          "     *",
          "     * @param key {String} The name of the style attribute.",
          "     * @param value {String} The value.",
          "     "
        ],
        "@description": [
          {
            "name": "@description",
            "body": "<p>Set the style to all blockers (blocker and content blocker).</p>"
          }
        ],
        "@param": [
          {
            "name": "@param",
            "body": "key {String} The name of the style attribute.",
            "paramName": "key",
            "description": " The name of the style attribute.",
            "type": "string"
          },
          {
            "name": "@param",
            "body": "value {String} The value.",
            "paramName": "value",
            "description": " The value.",
            "type": "string"
          }
        ]
      },
      "access": "private",
      "location": {
        "start": {
          "line": 232,
          "column": 4,
          "index": 6186
        },
        "end": {
          "line": 239,
          "column": 5,
          "index": 6405
        }
      },
      "type": "function",
      "params": [
        {
          "name": "key",
          "type": "string"
        },
        {
          "name": "value",
          "type": "string"
        }
      ],
      "appearsIn": []
    },
    "_backupActiveWidget": {
      "jsdoc": {
        "raw": [
          "*",
          "     * Backup the current active and focused widget.",
          "     "
        ],
        "@description": [
          {
            "name": "@description",
            "body": "<p>Backup the current active and focused widget.</p>"
          }
        ]
      },
      "access": "protected",
      "location": {
        "start": {
          "line": 244,
          "column": 4,
          "index": 6481
        },
        "end": {
          "line": 267,
          "column": 5,
          "index": 7104
        }
      },
      "type": "function",
      "params": [],
      "appearsIn": []
    },
    "_restoreActiveWidget": {
      "jsdoc": {
        "raw": [
          "*",
          "     * Restore the current active and focused widget.",
          "     "
        ],
        "@description": [
          {
            "name": "@description",
            "body": "<p>Restore the current active and focused widget.</p>"
          }
        ]
      },
      "access": "protected",
      "location": {
        "start": {
          "line": 272,
          "column": 4,
          "index": 7181
        },
        "end": {
          "line": 292,
          "column": 5,
          "index": 7730
        }
      },
      "type": "function",
      "params": [],
      "appearsIn": []
    },
    "__createBlockerElement": {
      "jsdoc": {
        "raw": [
          "*",
          "     * Creates the blocker element.",
          "     *",
          "     * @return {qx.html.Element} The blocker element",
          "     "
        ],
        "@description": [
          {
            "name": "@description",
            "body": "<p>Creates the blocker element.</p>"
          }
        ],
        "@return": [
          {
            "name": "@return",
            "body": "{qx.html.Element} The blocker element",
            "type": "qx.html.Element",
            "description": "The blocker element"
          }
        ]
      },
      "access": "private",
      "location": {
        "start": {
          "line": 299,
          "column": 4,
          "index": 7849
        },
        "end": {
          "line": 301,
          "column": 5,
          "index": 7951
        }
      },
      "type": "function",
      "params": [],
      "returnType": {
        "type": "qx.html.Element"
      },
      "appearsIn": []
    },
    "getBlockerElement": {
      "jsdoc": {
        "raw": [
          "*",
          "     * Get/create the blocker element",
          "     *",
          "     * @param widget {qx.ui.core.Widget} The blocker will be added to this",
          "     * widget's content element",
          "     * @return {qx.html.Element} The blocker element",
          "     "
        ],
        "@description": [
          {
            "name": "@description",
            "body": "<p>Get/create the blocker element</p>"
          }
        ],
        "@param": [
          {
            "name": "@param",
            "body": "widget {qx.ui.core.Widget} The blocker will be added to this\n widget's content element",
            "paramName": "widget",
            "description": " The blocker will be added to this\n widget's content element",
            "type": "qx.ui.core.Widget"
          }
        ],
        "@return": [
          {
            "name": "@return",
            "body": "{qx.html.Element} The blocker element",
            "type": "qx.html.Element",
            "description": "The blocker element"
          }
        ]
      },
      "access": "public",
      "location": {
        "start": {
          "line": 310,
          "column": 4,
          "index": 8179
        },
        "end": {
          "line": 327,
          "column": 5,
          "index": 8655
        }
      },
      "type": "function",
      "params": [
        {
          "name": "widget",
          "type": "qx.ui.core.Widget"
        }
      ],
      "returnType": {
        "type": "qx.html.Element"
      },
      "appearsIn": []
    },
    "block": {
      "jsdoc": {
        "raw": [
          "*",
          "     * Block all events from this widget by placing a transparent overlay widget,",
          "     * which receives all events, exactly over the widget.",
          "     "
        ],
        "@description": [
          {
            "name": "@description",
            "body": "<p>Block all events from this widget by placing a transparent overlay widget,\n which receives all events, exactly over the widget.</p>"
          }
        ]
      },
      "access": "public",
      "location": {
        "start": {
          "line": 333,
          "column": 4,
          "index": 8819
        },
        "end": {
          "line": 335,
          "column": 5,
          "index": 8855
        }
      },
      "type": "function",
      "params": [],
      "appearsIn": []
    },
    "_block": {
      "jsdoc": {
        "raw": [
          "*",
          "     * Adds the blocker to the appropriate element and includes it.",
          "     *",
          "     * @param zIndex {Number} All child widgets with a zIndex below this value will be blocked",
          "     * @param blockContent {Boolean} append the blocker to the widget's content if true",
          "     "
        ],
        "@description": [
          {
            "name": "@description",
            "body": "<p>Adds the blocker to the appropriate element and includes it.</p>"
          }
        ],
        "@param": [
          {
            "name": "@param",
            "body": "zIndex {Number} All child widgets with a zIndex below this value will be blocked",
            "paramName": "zIndex",
            "description": " All child widgets with a zIndex below this value will be blocked",
            "type": "number"
          },
          {
            "name": "@param",
            "body": "blockContent {Boolean} append the blocker to the widget's content if true",
            "paramName": "blockContent",
            "description": " append the blocker to the widget's content if true",
            "type": "boolean"
          }
        ]
      },
      "access": "protected",
      "location": {
        "start": {
          "line": 343,
          "column": 4,
          "index": 9136
        },
        "end": {
          "line": 391,
          "column": 5,
          "index": 10639
        }
      },
      "type": "function",
      "params": [
        {
          "name": "zIndex",
          "type": "number"
        },
        {
          "name": "blockContent",
          "type": "boolean"
        }
      ],
      "appearsIn": []
    },
    "isBlocked": {
      "jsdoc": {
        "raw": [
          "*",
          "     * Returns whether the widget is blocked.",
          "     *",
          "     * @return {Boolean} Whether the widget is blocked.",
          "     "
        ],
        "@description": [
          {
            "name": "@description",
            "body": "<p>Returns whether the widget is blocked.</p>"
          }
        ],
        "@return": [
          {
            "name": "@return",
            "body": "{Boolean} Whether the widget is blocked.",
            "type": "boolean",
            "description": "Whether the widget is blocked."
          }
        ]
      },
      "access": "public",
      "location": {
        "start": {
          "line": 398,
          "column": 4,
          "index": 10771
        },
        "end": {
          "line": 400,
          "column": 5,
          "index": 10828
        }
      },
      "type": "function",
      "params": [],
      "returnType": {
        "type": "boolean"
      },
      "appearsIn": []
    },
    "unblock": {
      "jsdoc": {
        "raw": [
          "*",
          "     * Unblock the widget blocked by {@link #block}, but it takes care of",
          "     * the amount of {@link #block} calls. The blocker is only removed if",
          "     * the number of {@link #unblock} calls is identical to {@link #block} calls.",
          "     "
        ],
        "@description": [
          {
            "name": "@description",
            "body": "<p>Unblock the widget blocked by {@link #block}, but it takes care of\n the amount of {@link #block} calls. The blocker is only removed if\n the number of {@link #unblock} calls is identical to {@link #block} calls.</p>"
          }
        ]
      },
      "access": "public",
      "location": {
        "start": {
          "line": 407,
          "column": 4,
          "index": 11081
        },
        "end": {
          "line": 422,
          "column": 5,
          "index": 11433
        }
      },
      "type": "function",
      "params": [],
      "appearsIn": []
    },
    "forceUnblock": {
      "jsdoc": {
        "raw": [
          "*",
          "     * Unblock the widget blocked by {@link #block}, but it doesn't take care of",
          "     * the amount of {@link #block} calls. The blocker is directly removed.",
          "     "
        ],
        "@description": [
          {
            "name": "@description",
            "body": "<p>Unblock the widget blocked by {@link #block}, but it doesn't take care of\n the amount of {@link #block} calls. The blocker is directly removed.</p>"
          }
        ]
      },
      "access": "public",
      "location": {
        "start": {
          "line": 428,
          "column": 4,
          "index": 11613
        },
        "end": {
          "line": 440,
          "column": 5,
          "index": 11892
        }
      },
      "type": "function",
      "params": [],
      "appearsIn": []
    },
    "__unblock": {
      "jsdoc": {
        "raw": [
          "*",
          "     * Unblock the widget blocked by {@link #block}.",
          "     "
        ],
        "@description": [
          {
            "name": "@description",
            "body": "<p>Unblock the widget blocked by {@link #block}.</p>"
          }
        ]
      },
      "access": "private",
      "location": {
        "start": {
          "line": 445,
          "column": 4,
          "index": 11968
        },
        "end": {
          "line": 459,
          "column": 5,
          "index": 12512
        }
      },
      "type": "function",
      "params": [],
      "appearsIn": []
    },
    "blockContent": {
      "jsdoc": {
        "raw": [
          "*",
          "     * Block direct child widgets with a zIndex below <code>zIndex</code>",
          "     *",
          "     * @param zIndex {Integer} All child widgets with a zIndex below this value",
          "     *     will be blocked",
          "     "
        ],
        "@description": [
          {
            "name": "@description",
            "body": "<p>Block direct child widgets with a zIndex below <code>zIndex</code></p>"
          }
        ],
        "@param": [
          {
            "name": "@param",
            "body": "zIndex {Integer} All child widgets with a zIndex below this value\n     will be blocked",
            "paramName": "zIndex",
            "description": " All child widgets with a zIndex below this value\n     will be blocked",
            "type": "Integer"
          }
        ]
      },
      "access": "public",
      "location": {
        "start": {
          "line": 467,
          "column": 4,
          "index": 12723
        },
        "end": {
          "line": 469,
          "column": 5,
          "index": 12784
        }
      },
      "type": "function",
      "params": [
        {
          "name": "zIndex",
          "type": "Integer"
        }
      ],
      "appearsIn": []
    },
    "__stopTabEvent": {
      "jsdoc": {
        "raw": [
          "*",
          "     * Stops the passed \"Tab\" event.",
          "     *",
          "     * @param e {qx.event.type.KeySequence} event to stop.",
          "     "
        ],
        "@description": [
          {
            "name": "@description",
            "body": "<p>Stops the passed \"Tab\" event.</p>"
          }
        ],
        "@param": [
          {
            "name": "@param",
            "body": "e {qx.event.type.KeySequence} event to stop.",
            "paramName": "e",
            "description": " event to stop.",
            "type": "qx.event.type.KeySequence"
          }
        ]
      },
      "access": "private",
      "location": {
        "start": {
          "line": 476,
          "column": 4,
          "index": 12910
        },
        "end": {
          "line": 480,
          "column": 5,
          "index": 13004
        }
      },
      "type": "function",
      "params": [
        {
          "name": "e",
          "type": "qx.event.type.KeySequence"
        }
      ],
      "appearsIn": []
    },
    "__activateBlockerElement": {
      "jsdoc": {
        "raw": [
          "*",
          "     * Sets the blocker element to active.",
          "     "
        ],
        "@description": [
          {
            "name": "@description",
            "body": "<p>Sets the blocker element to active.</p>"
          }
        ]
      },
      "access": "private",
      "location": {
        "start": {
          "line": 485,
          "column": 4,
          "index": 13070
        },
        "end": {
          "line": 504,
          "column": 5,
          "index": 13820
        }
      },
      "type": "function",
      "params": [],
      "appearsIn": []
    }
  },
  "destruct": {
    "type": "function",
    "params": [],
    "location": {
      "start": {
        "line": 513,
        "column": 2,
        "index": 14016
      },
      "end": {
        "line": 532,
        "column": 3,
        "index": 14797
      }
    }
  },
  "statics": {}
}